litepipeline/__init__.py
litepipeline/version.py
litepipeline/manager/README.md
litepipeline/manager/__init__.py
litepipeline/manager/config.py
litepipeline/manager/configuration.yml.temp
litepipeline/manager/install_systemd_service.sh
litepipeline/manager/litepipeline-manager.service.temp
litepipeline/manager/logger.py
litepipeline/manager/manager.py
litepipeline/manager/manager.sh
litepipeline/manager/uninstall_systemd_service.sh
litepipeline/manager/db/__init__.py
litepipeline/manager/db/sqlite_interface.py
litepipeline/manager/handlers/__init__.py
litepipeline/manager/handlers/application.py
litepipeline/manager/handlers/base.py
litepipeline/manager/handlers/info.py
litepipeline/manager/handlers/schedule.py
litepipeline/manager/handlers/task.py
litepipeline/manager/models/__init__.py
litepipeline/manager/models/applications.py
litepipeline/manager/models/schedules.py
litepipeline/manager/models/tasks.py
litepipeline/manager/utils/__init__.py
litepipeline/manager/utils/common.py
litepipeline/manager/utils/listener.py
litepipeline/manager/utils/persistent_config.py
litepipeline/manager/utils/scheduler.py
litepipeline/node/README.md
litepipeline/node/__init__.py
litepipeline/node/config.py
litepipeline/node/configuration.yml.temp
litepipeline/node/install_systemd_service.sh
litepipeline/node/litepipeline-node.service.temp
litepipeline/node/logger.py
litepipeline/node/node.py
litepipeline/node/node.sh
litepipeline/node/uninstall_systemd_service.sh
litepipeline/node/handlers/__init__.py
litepipeline/node/handlers/action.py
litepipeline/node/handlers/base.py
litepipeline/node/handlers/info.py
litepipeline/node/handlers/task.py
litepipeline/node/utils/__init__.py
litepipeline/node/utils/apps_manager.py
litepipeline/node/utils/common.py
litepipeline/node/utils/executor.py
litepipeline/node/utils/persistent_config.py
litepipeline/node/utils/registrant.py
litepipeline/node/utils/workspace_manager.py
litepipeline/tool/__init__.py
litepipeline/tool/liteconfig.py
litepipeline-0.0.17.dist-info/METADATA
litepipeline-0.0.17.dist-info/WHEEL
litepipeline-0.0.17.dist-info/entry_points.txt
litepipeline-0.0.17.dist-info/top_level.txt
litepipeline-0.0.17.dist-info/RECORD
