Metadata-Version: 2.1
Name: litepipeline
Version: 0.0.17
Summary: LitePipeline: distributed pipeline system
Home-page: https://github.com/fiefdx/LitePipeline
Author: fiefdx
Author-email: fiefdx@163.com
License: MIT
Platform: UNKNOWN
Classifier: License :: OSI Approved :: MIT License
Classifier: Programming Language :: Python :: 3
Classifier: Programming Language :: Python :: 3.7
Requires-Dist: progress (>=1.5)
Requires-Dist: requests (>=2.22.0)
Requires-Dist: tornado
Requires-Dist: pyYAML
Requires-Dist: tinydb
Requires-Dist: sqlalchemy
Requires-Dist: tornado-discovery
